Metadata-Version: 2.1
Name: dgpython-local
Version: 0.1.0
Summary: local module definitions for dataguzzler python
Home-page: http://thermal.cnde.iastate.edu
Author: Stephen D. Holland
Classifier: Development Status :: 3 - Alpha
Classifier: License :: OSI Approved :: BSD License
Requires-Python: >=3.8
License-File: LICENSE
